setup.cfg
setup.py
traggr.py
nose_traggr.egg-info/PKG-INFO
nose_traggr.egg-info/SOURCES.txt
nose_traggr.egg-info/dependency_links.txt
nose_traggr.egg-info/entry_points.txt
nose_traggr.egg-info/requires.txt
nose_traggr.egg-info/top_level.txt