Metadata-Version: 1.0
Name: nose-traggr
Version: 0.4.2
Summary: Nose plugin for posting results into Test Results Aggregation system
Home-page: https://github.com/witalick/nose-traggr
Author: Vitaliy Yakoviv
Author-email: witalick@gmail.com
License: UNKNOWN
Keywords: nose,plugin,testing,reporting
Platform: UNKNOWN
